README.md
setup.cfg
setup.py
src/ehttp_executor/__init__.py
src/ehttp_executor/ehttp_caller.py
src/ehttp_executor.egg-info/PKG-INFO
src/ehttp_executor.egg-info/SOURCES.txt
src/ehttp_executor.egg-info/dependency_links.txt
src/ehttp_executor.egg-info/requires.txt
src/ehttp_executor.egg-info/top_level.txt