Metadata-Version: 2.1
Name: ehttp-executor
Version: 1.0.0
Summary: Execute API method by HTTP
Home-page: https://www.pepsi.com/
Author: Eugenia Morales
Author-email: eugeniamorales251@gmail.com
License: MIT
Keywords: example project
Platform: UNKNOWN
Classifier: License :: OSI Approved :: MIT License
Classifier: Programming Language :: Python
Classifier: Programming Language :: Python :: 3
